Workbook

Sheet Start Here
B2: Budget by Paycheck
B3: Works in Microsoft Excel AND Google Sheets. Undated - start any payday, any year.
B5: QUICK START
B6: 1. Setup tab - pick your pay frequency, enter your next payday and your usual paycheck amount.
B7: 2. Plan tab - list each bill or expense and type the paycheck number (1, 2, 3...) that will pay for it.
B8: 3. Spending tab - log what you actually spend. The paycheck number fills in automatically from the date.
B9: 4. Dashboard tab - see planned vs actual for every paycheck and every category.
B11: LEGEND
B12: Cream cells = type here. Everything else calculates automatically - no need to touch it.
B13: The Plan and Spending tabs each contain one grey example row. Replace it with your own numbers.
B15: USING GOOGLE SHEETS?
B16: Go to sheets.new > File > Import > Upload > choose this file > 'Replace spreadsheet'.
... B23: Semi-monthly pays on your chosen start day and the 15 days that follow it (e.g. the 1st and the 16th).

Sheet Setup
A1: Setup
A4: Pay frequency | B4: Biweekly | C4: Weekly, Biweekly, Semi-monthly, or Monthly
A5: First payday | B5: 46269 | C5: Your next payday - every pay date builds from this
A6: Usual paycheck amount | B6: 2000 | C6: Used for any paycheck you don't override on the Paychecks tab
A10: Spending categories | C10: Edit freely - dropdowns on the Plan and Spending tabs follow this list
A11: Rent / Mortgage
A12: Utilities
A13: Groceries
A14: Transport
A15: Insurance
A16: Debt Payments
A17: Subscriptions
A18: Dining Out
A19: Health
A20: Savings
A21: Giving
A22: Fun
... A25: Misc

Sheet Paychecks
A1: # | B1: Pay Date | C1: Income (override) | D1: Income Used | E1: Planned Spending | F1: Actual Spending | G1: Planned Leftover | H1: Actual Leftover
A2: 1 | B2: =IF(Setup!$B$4="Weekly",Setup!$B$5+(A2-1)*7,IF(Setup!$B$4="Biweekly",Setup!$B$5+(A2-1)*14,IF(Setup!$B$4="Monthly",EDATE(Setup!$B$5,A2-1),IF(MOD(A2,2)=1,EDATE(Setup!$B$5,(A2-1)/2),EDATE(Setup!$B$5,(A2-2)/2)+15)))) -> 46269 | D2: =IF(AND(C2="",E2=0,F2=0),0,IF(C2="",Setup!$B$6,C2)) -> 2000 | E2: =SUMIFS(Plan!$D:$D,Plan!$A:$A,A2) -> 1200 | F2: =SUMIFS(Spending!$D:$D,Spending!$E:$E,A2) -> 84.5 | G2: =IF(D2=0,0,D2-E2) -> 800 | H2: =IF(D2=0,0,D2-F2) -> 1915.5
A3: 2 | B3: =IF(Setup!$B$4="Weekly",Setup!$B$5+(A3-1)*7,IF(Setup!$B$4="Biweekly",Setup!$B$5+(A3-1)*14,IF(Setup!$B$4="Monthly",EDATE(Setup!$B$5,A3-1),IF(MOD(A3,2)=1,EDATE(Setup!$B$5,(A3-1)/2),EDATE(Setup!$B$5,(A3-2)/2)+15)))) -> 46283 | D3: =IF(AND(C3="",E3=0,F3=0),0,IF(C3="",Setup!$B$6,C3)) -> 0 | E3: =SUMIFS(Plan!$D:$D,Plan!$A:$A,A3) -> 0 | F3: =SUMIFS(Spending!$D:$D,Spending!$E:$E,A3) -> 0 | G3: =IF(D3=0,0,D3-E3) -> 0 | H3: =IF(D3=0,0,D3-F3) -> 0
A4: 3 | B4: =IF(Setup!$B$4="Weekly",Setup!$B$5+(A4-1)*7,IF(Setup!$B$4="Biweekly",Setup!$B$5+(A4-1)*14,IF(Setup!$B$4="Monthly",EDATE(Setup!$B$5,A4-1),IF(MOD(A4,2)=1,EDATE(Setup!$B$5,(A4-1)/2),EDATE(Setup!$B$5,(A4-2)/2)+15)))) -> 46297 | D4: =IF(AND(C4="",E4=0,F4=0),0,IF(C4="",Setup!$B$6,C4)) -> 0 | E4: =SUMIFS(Plan!$D:$D,Plan!$A:$A,A4) -> 0 | F4: =SUMIFS(Spending!$D:$D,Spending!$E:$E,A4) -> 0 | G4: =IF(D4=0,0,D4-E4) -> 0 | H4: =IF(D4=0,0,D4-F4) -> 0
A5: 4 | B5: =IF(Setup!$B$4="Weekly",Setup!$B$5+(A5-1)*7,IF(Setup!$B$4="Biweekly",Setup!$B$5+(A5-1)*14,IF(Setup!$B$4="Monthly",EDATE(Setup!$B$5,A5-1),IF(MOD(A5,2)=1,EDATE(Setup!$B$5,(A5-1)/2),EDATE(Setup!$B$5,(A5-2)/2)+15)))) -> 46311 | D5: =IF(AND(C5="",E5=0,F5=0),0,IF(C5="",Setup!$B$6,C5)) -> 0 | E5: =SUMIFS(Plan!$D:$D,Plan!$A:$A,A5) -> 0 | F5: =SUMIFS(Spending!$D:$D,Spending!$E:$E,A5) -> 0 | G5: =IF(D5=0,0,D5-E5) -> 0 | H5: =IF(D5=0,0,D5-F5) -> 0
A6: 5 | B6: =IF(Setup!$B$4="Weekly",Setup!$B$5+(A6-1)*7,IF(Setup!$B$4="Biweekly",Setup!$B$5+(A6-1)*14,IF(Setup!$B$4="Monthly",EDATE(Setup!$B$5,A6-1),IF(MOD(A6,2)=1,EDATE(Setup!$B$5,(A6-1)/2),EDATE(Setup!$B$5,(A6-2)/2)+15)))) -> 46325 | D6: =IF(AND(C6="",E6=0,F6=0),0,IF(C6="",Setup!$B$6,C6)) -> 0 | E6: =SUMIFS(Plan!$D:$D,Plan!$A:$A,A6) -> 0 | F6: =SUMIFS(Spending!$D:$D,Spending!$E:$E,A6) -> 0 | G6: =IF(D6=0,0,D6-E6) -> 0 | H6: =IF(D6=0,0,D6-F6) -> 0
A7: 6 | B7: =IF(Setup!$B$4="Weekly",Setup!$B$5+(A7-1)*7,IF(Setup!$B$4="Biweekly",Setup!$B$5+(A7-1)*14,IF(Setup!$B$4="Monthly",EDATE(Setup!$B$5,A7-1),IF(MOD(A7,2)=1,EDATE(Setup!$B$5,(A7-1)/2),EDATE(Setup!$B$5,(A7-2)/2)+15)))) -> 46339 | D7: =IF(AND(C7="",E7=0,F7=0),0,IF(C7="",Setup!$B$6,C7)) -> 0 | E7: =SUMIFS(Plan!$D:$D,Plan!$A:$A,A7) -> 0 | F7: =SUMIFS(Spending!$D:$D,Spending!$E:$E,A7) -> 0 | G7: =IF(D7=0,0,D7-E7) -> 0 | H7: =IF(D7=0,0,D7-F7) -> 0
A8: 7 | B8: =IF(Setup!$B$4="Weekly",Setup!$B$5+(A8-1)*7,IF(Setup!$B$4="Biweekly",Setup!$B$5+(A8-1)*14,IF(Setup!$B$4="Monthly",EDATE(Setup!$B$5,A8-1),IF(MOD(A8,2)=1,EDATE(Setup!$B$5,(A8-1)/2),EDATE(Setup!$B$5,(A8-2)/2)+15)))) -> 46353 | D8: =IF(AND(C8="",E8=0,F8=0),0,IF(C8="",Setup!$B$6,C8)) -> 0 | E8: =SUMIFS(Plan!$D:$D,Plan!$A:$A,A8) -> 0 | F8: =SUMIFS(Spending!$D:$D,Spending!$E:$E,A8) -> 0 | G8: =IF(D8=0,0,D8-E8) -> 0 | H8: =IF(D8=0,0,D8-F8) -> 0
A9: 8 | B9: =IF(Setup!$B$4="Weekly",Setup!$B$5+(A9-1)*7,IF(Setup!$B$4="Biweekly",Setup!$B$5+(A9-1)*14,IF(Setup!$B$4="Monthly",EDATE(Setup!$B$5,A9-1),IF(MOD(A9,2)=1,EDATE(Setup!$B$5,(A9-1)/2),EDATE(Setup!$B$5,(A9-2)/2)+15)))) -> 46367 | D9: =IF(AND(C9="",E9=0,F9=0),0,IF(C9="",Setup!$B$6,C9)) -> 0 | E9: =SUMIFS(Plan!$D:$D,Plan!$A:$A,A9) -> 0 | F9: =SUMIFS(Spending!$D:$D,Spending!$E:$E,A9) -> 0 | G9: =IF(D9=0,0,D9-E9) -> 0 | H9: =IF(D9=0,0,D9-F9) -> 0
A10: 9 | B10: =IF(Setup!$B$4="Weekly",Setup!$B$5+(A10-1)*7,IF(Setup!$B$4="Biweekly",Setup!$B$5+(A10-1)*14,IF(Setup!$B$4="Monthly",EDATE(Setup!$B$5,A10-1),IF(MOD(A10,2)=1,EDATE(Setup!$B$5,(A10-1)/2),EDATE(Setup!$B$5,(A10-2)/2)+15)))) -> 46381 | D10: =IF(AND(C10="",E10=0,F10=0),0,IF(C10="",Setup!$B$6,C10)) -> 0 | E10: =SUMIFS(Plan!$D:$D,Plan!$A:$A,A10) -> 0 | F10: =SUMIFS(Spending!$D:$D,Spending!$E:$E,A10) -> 0 | G10: =IF(D10=0,0,D10-E10) -> 0 | H10: =IF(D10=0,0,D10-F10) -> 0
A11: 10 | B11: =IF(Setup!$B$4="Weekly",Setup!$B$5+(A11-1)*7,IF(Setup!$B$4="Biweekly",Setup!$B$5+(A11-1)*14,IF(Setup!$B$4="Monthly",EDATE(Setup!$B$5,A11-1),IF(MOD(A11,2)=1,EDATE(Setup!$B$5,(A11-1)/2),EDATE(Setup!$B$5,(A11-2)/2)+15)))) -> 46395 | D11: =IF(AND(C11="",E11=0,F11=0),0,IF(C11="",Setup!$B$6,C11)) -> 0 | E11: =SUMIFS(Plan!$D:$D,Plan!$A:$A,A11) -> 0 | F11: =SUMIFS(Spending!$D:$D,Spending!$E:$E,A11) -> 0 | G11: =IF(D11=0,0,D11-E11) -> 0 | H11: =IF(D11=0,0,D11-F11) -> 0
A12: 11 | B12: =IF(Setup!$B$4="Weekly",Setup!$B$5+(A12-1)*7,IF(Setup!$B$4="Biweekly",Setup!$B$5+(A12-1)*14,IF(Setup!$B$4="Monthly",EDATE(Setup!$B$5,A12-1),IF(MOD(A12,2)=1,EDATE(Setup!$B$5,(A12-1)/2),EDATE(Setup!$B$5,(A12-2)/2)+15)))) -> 46409 | D12: =IF(AND(C12="",E12=0,F12=0),0,IF(C12="",Setup!$B$6,C12)) -> 0 | E12: =SUMIFS(Plan!$D:$D,Plan!$A:$A,A12) -> 0 | F12: =SUMIFS(Spending!$D:$D,Spending!$E:$E,A12) -> 0 | G12: =IF(D12=0,0,D12-E12) -> 0 | H12: =IF(D12=0,0,D12-F12) -> 0
A13: 12 | B13: =IF(Setup!$B$4="Weekly",Setup!$B$5+(A13-1)*7,IF(Setup!$B$4="Biweekly",Setup!$B$5+(A13-1)*14,IF(Setup!$B$4="Monthly",EDATE(Setup!$B$5,A13-1),IF(MOD(A13,2)=1,EDATE(Setup!$B$5,(A13-1)/2),EDATE(Setup!$B$5,(A13-2)/2)+15)))) -> 46423 | D13: =IF(AND(C13="",E13=0,F13=0),0,IF(C13="",Setup!$B$6,C13)) -> 0 | E13: =SUMIFS(Plan!$D:$D,Plan!$A:$A,A13) -> 0 | F13: =SUMIFS(Spending!$D:$D,Spending!$E:$E,A13) -> 0 | G13: =IF(D13=0,0,D13-E13) -> 0 | H13: =IF(D13=0,0,D13-F13) -> 0
... A27: 26 | B27: =IF(Setup!$B$4="Weekly",Setup!$B$5+(A27-1)*7,IF(Setup!$B$4="Biweekly",Setup!$B$5+(A27-1)*14,IF(Setup!$B$4="Monthly",EDATE(Setup!$B$5,A27-1),IF(MOD(A27,2)=1,EDATE(Setup!$B$5,(A27-1)/2),EDATE(Setup!$B$5,(A27-2)/2)+15)))) -> 46619 | D27: =IF(AND(C27="",E27=0,F27=0),0,IF(C27="",Setup!$B$6,C27)) -> 0 | E27: =SUMIFS(Plan!$D:$D,Plan!$A:$A,A27) -> 0 | F27: =SUMIFS(Spending!$D:$D,Spending!$E:$E,A27) -> 0 | G27: =IF(D27=0,0,D27-E27) -> 0 | H27: =IF(D27=0,0,D27-F27) -> 0

Sheet Plan
A1: Paycheck # | B1: Bill / Item | C1: Category | D1: Planned Amount | E1: Pay Date
A2: 1 | B2: Rent - example row, replace me | C2: Rent / Mortgage | D2: 1200 | E2: =IF(A2="","",IFERROR(INDEX(Paychecks!$B$2:$B$27,MATCH(A2,Paychecks!$A$2:$A$27,0)),"")) -> 46269
E3: =IF(A3="","",IFERROR(INDEX(Paychecks!$B$2:$B$27,MATCH(A3,Paychecks!$A$2:$A$27,0)),""))
E4: =IF(A4="","",IFERROR(INDEX(Paychecks!$B$2:$B$27,MATCH(A4,Paychecks!$A$2:$A$27,0)),""))
E5: =IF(A5="","",IFERROR(INDEX(Paychecks!$B$2:$B$27,MATCH(A5,Paychecks!$A$2:$A$27,0)),""))
E6: =IF(A6="","",IFERROR(INDEX(Paychecks!$B$2:$B$27,MATCH(A6,Paychecks!$A$2:$A$27,0)),""))
E7: =IF(A7="","",IFERROR(INDEX(Paychecks!$B$2:$B$27,MATCH(A7,Paychecks!$A$2:$A$27,0)),""))
E8: =IF(A8="","",IFERROR(INDEX(Paychecks!$B$2:$B$27,MATCH(A8,Paychecks!$A$2:$A$27,0)),""))
E9: =IF(A9="","",IFERROR(INDEX(Paychecks!$B$2:$B$27,MATCH(A9,Paychecks!$A$2:$A$27,0)),""))
E10: =IF(A10="","",IFERROR(INDEX(Paychecks!$B$2:$B$27,MATCH(A10,Paychecks!$A$2:$A$27,0)),""))
E11: =IF(A11="","",IFERROR(INDEX(Paychecks!$B$2:$B$27,MATCH(A11,Paychecks!$A$2:$A$27,0)),""))
E12: =IF(A12="","",IFERROR(INDEX(Paychecks!$B$2:$B$27,MATCH(A12,Paychecks!$A$2:$A$27,0)),""))
E13: =IF(A13="","",IFERROR(INDEX(Paychecks!$B$2:$B$27,MATCH(A13,Paychecks!$A$2:$A$27,0)),""))
E14: =IF(A14="","",IFERROR(INDEX(Paychecks!$B$2:$B$27,MATCH(A14,Paychecks!$A$2:$A$27,0)),""))
... E121: =IF(A121="","",IFERROR(INDEX(Paychecks!$B$2:$B$27,MATCH(A121,Paychecks!$A$2:$A$27,0)),""))

Sheet Spending
A1: Date | B1: Description | C1: Category | D1: Amount | E1: Paycheck # (auto)
A2: 46271 | B2: Groceries - example row, replace me | C2: Groceries | D2: 84.5 | E2: =IF(A2="","",IFERROR(MATCH(A2,Paychecks!$B$2:$B$27,1),"")) -> 1
E3: =IF(A3="","",IFERROR(MATCH(A3,Paychecks!$B$2:$B$27,1),""))
E4: =IF(A4="","",IFERROR(MATCH(A4,Paychecks!$B$2:$B$27,1),""))
E5: =IF(A5="","",IFERROR(MATCH(A5,Paychecks!$B$2:$B$27,1),""))
E6: =IF(A6="","",IFERROR(MATCH(A6,Paychecks!$B$2:$B$27,1),""))
E7: =IF(A7="","",IFERROR(MATCH(A7,Paychecks!$B$2:$B$27,1),""))
E8: =IF(A8="","",IFERROR(MATCH(A8,Paychecks!$B$2:$B$27,1),""))
E9: =IF(A9="","",IFERROR(MATCH(A9,Paychecks!$B$2:$B$27,1),""))
E10: =IF(A10="","",IFERROR(MATCH(A10,Paychecks!$B$2:$B$27,1),""))
E11: =IF(A11="","",IFERROR(MATCH(A11,Paychecks!$B$2:$B$27,1),""))
E12: =IF(A12="","",IFERROR(MATCH(A12,Paychecks!$B$2:$B$27,1),""))
E13: =IF(A13="","",IFERROR(MATCH(A13,Paychecks!$B$2:$B$27,1),""))
E14: =IF(A14="","",IFERROR(MATCH(A14,Paychecks!$B$2:$B$27,1),""))
... E301: =IF(A301="","",IFERROR(MATCH(A301,Paychecks!$B$2:$B$27,1),""))

Sheet Dashboard
A1: Dashboard
A3: Total income | B3: Total planned | C3: Total spent | D3: Leftover (actual)
A4: =SUM(Paychecks!D2:D27) -> 2000 | B4: =SUM(Paychecks!E2:E27) -> 1200 | C4: =SUM(Paychecks!F2:F27) -> 84.5 | D4: =SUM(Paychecks!H2:H27) -> 1915.5
A6: By category
A7: Category | B7: Planned | C7: Actual | D7: Difference
A8: =IF(Setup!A11="","",Setup!A11) -> Rent / Mortgage | B8: =IF($A8="","",SUMIFS(Plan!$D:$D,Plan!$C:$C,$A8)) -> 1200 | C8: =IF($A8="","",SUMIFS(Spending!$D:$D,Spending!$C:$C,$A8)) -> 0 | D8: =IF($A8="","",B8-C8) -> 1200
A9: =IF(Setup!A12="","",Setup!A12) -> Utilities | B9: =IF($A9="","",SUMIFS(Plan!$D:$D,Plan!$C:$C,$A9)) -> 0 | C9: =IF($A9="","",SUMIFS(Spending!$D:$D,Spending!$C:$C,$A9)) -> 0 | D9: =IF($A9="","",B9-C9) -> 0
A10: =IF(Setup!A13="","",Setup!A13) -> Groceries | B10: =IF($A10="","",SUMIFS(Plan!$D:$D,Plan!$C:$C,$A10)) -> 0 | C10: =IF($A10="","",SUMIFS(Spending!$D:$D,Spending!$C:$C,$A10)) -> 84.5 | D10: =IF($A10="","",B10-C10) -> -84.5
A11: =IF(Setup!A14="","",Setup!A14) -> Transport | B11: =IF($A11="","",SUMIFS(Plan!$D:$D,Plan!$C:$C,$A11)) -> 0 | C11: =IF($A11="","",SUMIFS(Spending!$D:$D,Spending!$C:$C,$A11)) -> 0 | D11: =IF($A11="","",B11-C11) -> 0
A12: =IF(Setup!A15="","",Setup!A15) -> Insurance | B12: =IF($A12="","",SUMIFS(Plan!$D:$D,Plan!$C:$C,$A12)) -> 0 | C12: =IF($A12="","",SUMIFS(Spending!$D:$D,Spending!$C:$C,$A12)) -> 0 | D12: =IF($A12="","",B12-C12) -> 0
A13: =IF(Setup!A16="","",Setup!A16) -> Debt Payments | B13: =IF($A13="","",SUMIFS(Plan!$D:$D,Plan!$C:$C,$A13)) -> 0 | C13: =IF($A13="","",SUMIFS(Spending!$D:$D,Spending!$C:$C,$A13)) -> 0 | D13: =IF($A13="","",B13-C13) -> 0
A14: =IF(Setup!A17="","",Setup!A17) -> Subscriptions | B14: =IF($A14="","",SUMIFS(Plan!$D:$D,Plan!$C:$C,$A14)) -> 0 | C14: =IF($A14="","",SUMIFS(Spending!$D:$D,Spending!$C:$C,$A14)) -> 0 | D14: =IF($A14="","",B14-C14) -> 0
A15: =IF(Setup!A18="","",Setup!A18) -> Dining Out | B15: =IF($A15="","",SUMIFS(Plan!$D:$D,Plan!$C:$C,$A15)) -> 0 | C15: =IF($A15="","",SUMIFS(Spending!$D:$D,Spending!$C:$C,$A15)) -> 0 | D15: =IF($A15="","",B15-C15) -> 0
A16: =IF(Setup!A19="","",Setup!A19) -> Health | B16: =IF($A16="","",SUMIFS(Plan!$D:$D,Plan!$C:$C,$A16)) -> 0 | C16: =IF($A16="","",SUMIFS(Spending!$D:$D,Spending!$C:$C,$A16)) -> 0 | D16: =IF($A16="","",B16-C16) -> 0
A17: =IF(Setup!A20="","",Setup!A20) -> Savings | B17: =IF($A17="","",SUMIFS(Plan!$D:$D,Plan!$C:$C,$A17)) -> 0 | C17: =IF($A17="","",SUMIFS(Spending!$D:$D,Spending!$C:$C,$A17)) -> 0 | D17: =IF($A17="","",B17-C17) -> 0
A18: =IF(Setup!A21="","",Setup!A21) -> Giving | B18: =IF($A18="","",SUMIFS(Plan!$D:$D,Plan!$C:$C,$A18)) -> 0 | C18: =IF($A18="","",SUMIFS(Spending!$D:$D,Spending!$C:$C,$A18)) -> 0 | D18: =IF($A18="","",B18-C18) -> 0
A19: =IF(Setup!A22="","",Setup!A22) -> Fun | B19: =IF($A19="","",SUMIFS(Plan!$D:$D,Plan!$C:$C,$A19)) -> 0 | C19: =IF($A19="","",SUMIFS(Spending!$D:$D,Spending!$C:$C,$A19)) -> 0 | D19: =IF($A19="","",B19-C19) -> 0
... A27: =IF(Setup!A30="","",Setup!A30) | B27: =IF($A27="","",SUMIFS(Plan!$D:$D,Plan!$C:$C,$A27)) | C27: =IF($A27="","",SUMIFS(Spending!$D:$D,Spending!$C:$C,$A27)) | D27: =IF($A27="","",B27-C27)
A30: By paycheck
A31: # | B31: Pay Date | C31: Income | D31: Planned | E31: Actual | F31: Leftover
A32: =Paychecks!A2 -> 1 | B32: =Paychecks!B2 -> 46269 | C32: =Paychecks!D2 -> 2000 | D32: =Paychecks!E2 -> 1200 | E32: =Paychecks!F2 -> 84.5 | F32: =Paychecks!H2 -> 1915.5
A33: =Paychecks!A3 -> 2 | B33: =Paychecks!B3 -> 46283 | C33: =Paychecks!D3 -> 0 | D33: =Paychecks!E3 -> 0 | E33: =Paychecks!F3 -> 0 | F33: =Paychecks!H3 -> 0
A34: =Paychecks!A4 -> 3 | B34: =Paychecks!B4 -> 46297 | C34: =Paychecks!D4 -> 0 | D34: =Paychecks!E4 -> 0 | E34: =Paychecks!F4 -> 0 | F34: =Paychecks!H4 -> 0
A35: =Paychecks!A5 -> 4 | B35: =Paychecks!B5 -> 46311 | C35: =Paychecks!D5 -> 0 | D35: =Paychecks!E5 -> 0 | E35: =Paychecks!F5 -> 0 | F35: =Paychecks!H5 -> 0
A36: =Paychecks!A6 -> 5 | B36: =Paychecks!B6 -> 46325 | C36: =Paychecks!D6 -> 0 | D36: =Paychecks!E6 -> 0 | E36: =Paychecks!F6 -> 0 | F36: =Paychecks!H6 -> 0
A37: =Paychecks!A7 -> 6 | B37: =Paychecks!B7 -> 46339 | C37: =Paychecks!D7 -> 0 | D37: =Paychecks!E7 -> 0 | E37: =Paychecks!F7 -> 0 | F37: =Paychecks!H7 -> 0
A38: =Paychecks!A8 -> 7 | B38: =Paychecks!B8 -> 46353 | C38: =Paychecks!D8 -> 0 | D38: =Paychecks!E8 -> 0 | E38: =Paychecks!F8 -> 0 | F38: =Paychecks!H8 -> 0
A39: =Paychecks!A9 -> 8 | B39: =Paychecks!B9 -> 46367 | C39: =Paychecks!D9 -> 0 | D39: =Paychecks!E9 -> 0 | E39: =Paychecks!F9 -> 0 | F39: =Paychecks!H9 -> 0
A40: =Paychecks!A10 -> 9 | B40: =Paychecks!B10 -> 46381 | C40: =Paychecks!D10 -> 0 | D40: =Paychecks!E10 -> 0 | E40: =Paychecks!F10 -> 0 | F40: =Paychecks!H10 -> 0
A41: =Paychecks!A11 -> 10 | B41: =Paychecks!B11 -> 46395 | C41: =Paychecks!D11 -> 0 | D41: =Paychecks!E11 -> 0 | E41: =Paychecks!F11 -> 0 | F41: =Paychecks!H11 -> 0
A42: =Paychecks!A12 -> 11 | B42: =Paychecks!B12 -> 46409 | C42: =Paychecks!D12 -> 0 | D42: =Paychecks!E12 -> 0 | E42: =Paychecks!F12 -> 0 | F42: =Paychecks!H12 -> 0
A43: =Paychecks!A13 -> 12 | B43: =Paychecks!B13 -> 46423 | C43: =Paychecks!D13 -> 0 | D43: =Paychecks!E13 -> 0 | E43: =Paychecks!F13 -> 0 | F43: =Paychecks!H13 -> 0
... A57: =Paychecks!A27 -> 26 | B57: =Paychecks!B27 -> 46619 | C57: =Paychecks!D27 -> 0 | D57: =Paychecks!E27 -> 0 | E57: =Paychecks!F27 -> 0 | F57: =Paychecks!H27 -> 0
